polygons-0.3.5.dist-info/METADATA
polygons-0.3.5.dist-info/WHEEL
polygons/__init__.py
polygons/polygons.cpython-312-x86_64-linux-gnu.so
polygons-0.3.5.dist-info/RECORD
