Metadata-Version: 2.4
Name: polygons
Version: 0.3.5
Summary: Fast points-in-polygon test and distances to polygons.
Home-Page: https://github.com/bast/polygons
Author: Radovan Bast <bast@users.noreply.github.com>
Author-email: Radovan Bast <bast@users.noreply.github.com>
License: GPL-3.0-only
